JSNMF/__init__.py
JSNMF/model.py
JSNMF/utils.py
JSNMF_py-0.0.3.dist-info/LICENSE
JSNMF_py-0.0.3.dist-info/METADATA
JSNMF_py-0.0.3.dist-info/WHEEL
JSNMF_py-0.0.3.dist-info/top_level.txt
JSNMF_py-0.0.3.dist-info/RECORD
