Metadata-Version: 2.1
Name: JSNMF_py
Version: 0.0.3
Summary: JSNMF Python Implementation
Home-page: https://github.com/cuhklinlab/JSNMF_py
Author: Zexuan Sun
Author-email: zexuansun@outlook.com
License: UNKNOWN
Platform: UNKNOWN
Classifier: Programming Language :: Python :: 3
Classifier: License :: OSI Approved :: MIT License
Classifier: Operating System :: OS Independent
Requires-Python: >=3.6
License-File: LICENSE
